README.rst
setup.py
murphy/__init__.py
murphy/attributehandler.py
murphy/parsegtf.py
murphy.egg-info/PKG-INFO
murphy.egg-info/SOURCES.txt
murphy.egg-info/dependency_links.txt
murphy.egg-info/not-zip-safe
murphy.egg-info/requires.txt
murphy.egg-info/top_level.txt
murphy/Tree/__init__.py
murphy/Tree/intervalTree.py
murphy/tests/__init__.py
murphy/tests/test.gtf
murphy/tests/test_docstrings.py
murphy/tests/test_imports.py
murphy/tests/test_intervaltree.py