Metadata-Version: 1.1
Name: murphy
Version: 0.1
Summary: Generic tools to identify overlapping genomic regions
Home-page: https://github.com/drsuuzzz/murphy
Author: Suzy Stiegelmeyer
Author-email: drsuuzzz@gmail.com
License: Apache-2.0
Keywords: bioinformatics,interval overlap tree,binary tree,genomics
Platform: UNKNOWN
Classifier: Development Status :: 3 - Alpha
Classifier: Intended Audience :: Science/Research
Classifier: License :: OSI Approved :: Apache Software License
Classifier: Operating System :: OS Independent
Classifier: Programming Language :: Python :: 2.7
Classifier: Programming Language :: Python :: 3
Classifier: Topic :: Scientific/Engineering :: Bio-Informatics
